anodb.py
anodb-15.0.dist-info/licenses/LICENSE
anodb-15.0.dist-info/METADATA
anodb-15.0.dist-info/WHEEL
anodb-15.0.dist-info/top_level.txt
anodb-15.0.dist-info/RECORD
