Metadata-Version: 2.4
Name: anodb
Version: 15.0
Summary: Convenient Wrapper around AioSQL and a Database Connection
Author-email: Fabien Coelho <ano.db@coelho.net>
License-Expression: CC0-1.0
Project-URL: repository, https://github.com/zx80/anodb
Project-URL: documentation, https://zx80.github.io/anodb/
Project-URL: issues, https://github.com/zx80/anodb/issues
Project-URL: package, https://pypi.org/project/anodb/
Classifier: Development Status :: 5 - Production/Stable
Classifier: Intended Audience :: Developers
Classifier: Programming Language :: Python
Classifier: Programming Language :: SQL
Classifier: Topic :: Database :: Front-Ends
Classifier: Topic :: Software Development :: Libraries :: Python Modules
Requires-Python: >=3.10
License-File: LICENSE
Requires-Dist: aiosql>=15.0
Provides-Extra: dev
Requires-Dist: mypy; extra == "dev"
Requires-Dist: pyright; extra == "dev"
Requires-Dist: ruff; extra == "dev"
Requires-Dist: flake8; extra == "dev"
Requires-Dist: black; extra == "dev"
Requires-Dist: pymarkdownlnt; extra == "dev"
Requires-Dist: pytest; extra == "dev"
Requires-Dist: coverage; extra == "dev"
Requires-Dist: CacheToolsUtils; extra == "dev"
Provides-Extra: pub
Requires-Dist: build; extra == "pub"
Requires-Dist: twine; extra == "pub"
Requires-Dist: wheel; extra == "pub"
Provides-Extra: postgres
Requires-Dist: pytest-postgresql; extra == "postgres"
Requires-Dist: psycopg2>=2.9.10; implementation_name != "pypy" and extra == "postgres"
Requires-Dist: psycopg; extra == "postgres"
Requires-Dist: pygresql; extra == "postgres"
Requires-Dist: pg8000; extra == "postgres"
Provides-Extra: mysql
Requires-Dist: pytest-mysql; extra == "mysql"
Requires-Dist: mysqlclient; extra == "mysql"
Requires-Dist: pymysql; extra == "mysql"
Requires-Dist: mysql-connector; extra == "mysql"
Dynamic: license-file
